cs2tracker/__init__.py
cs2tracker/__main__.py
cs2tracker/_version.py
cs2tracker/config.py
cs2tracker/constants.py
cs2tracker/logs.py
cs2tracker/main.py
cs2tracker/app/__init__.py
cs2tracker/app/app.py
cs2tracker/app/editor_frame.py
cs2tracker/app/history_frame.py
cs2tracker/app/scraper_frame.py
cs2tracker/data/config.ini
cs2tracker/data/convert_inventory.js
cs2tracker/data/get_inventory.js
cs2tracker/data/icon.ico
cs2tracker/data/icon.png
cs2tracker/data/output.csv
cs2tracker/scraper/__init__.py
cs2tracker/scraper/background_task.py
cs2tracker/scraper/discord_notifier.py
cs2tracker/scraper/parser.py
cs2tracker/scraper/scraper.py
cs2tracker/util/__init__.py
cs2tracker/util/currency_conversion.py
cs2tracker/util/padded_console.py
cs2tracker/util/tkinter.py
cs2tracker-2.1.22.dist-info/licenses/LICENSE
cs2tracker-2.1.22.dist-info/METADATA
cs2tracker-2.1.22.dist-info/WHEEL
cs2tracker-2.1.22.dist-info/entry_points.txt
cs2tracker-2.1.22.dist-info/top_level.txt
cs2tracker-2.1.22.dist-info/RECORD
