Metadata-Version: 2.4
Name: cs2tracker
Version: 2.1.22
Summary: Tracking the steam market prices of CS2 items
Home-page: https://github.com/ashiven/cs2tracker
Author: Jannik Novak
Author-email: nevisha@pm.me
Classifier: Development Status :: 3 - Alpha
Classifier: License :: OSI Approved :: MIT License
Classifier: Programming Language :: Python :: 3.11
Requires-Python: >=3.11
License-File: LICENSE
Requires-Dist: numpy==1.26.4
Requires-Dist: beautifulsoup4==4.11.1
Requires-Dist: CurrencyConverter==0.17.9
Requires-Dist: matplotlib==3.7.0
Requires-Dist: Requests==2.31.0
Requires-Dist: rich==13.6.0
Requires-Dist: tenacity==8.2.2
Requires-Dist: urllib3==2.1.0
Requires-Dist: sv_ttk==2.6.1
Requires-Dist: tksheet==7.5.12
Requires-Dist: nodejs-bin==18.4.0a4
Requires-Dist: ttk-text==0.2.0
Requires-Dist: requests-cache==1.2.1
Dynamic: license-file
